README.txt
setup.cfg
setup.py
bit/__init__.py
bit.recipe.android_sdk.egg-info/PKG-INFO
bit.recipe.android_sdk.egg-info/SOURCES.txt
bit.recipe.android_sdk.egg-info/dependency_links.txt
bit.recipe.android_sdk.egg-info/entry_points.txt
bit.recipe.android_sdk.egg-info/namespace_packages.txt
bit.recipe.android_sdk.egg-info/not-zip-safe
bit.recipe.android_sdk.egg-info/requires.txt
bit.recipe.android_sdk.egg-info/top_level.txt
bit/recipe/__init__.py
bit/recipe/android_sdk/__init__.py
bit/recipe/android_sdk/install_android_sdk